aiosqlitepool/__init__.py
aiosqlitepool/client.py
aiosqlitepool/connection.py
aiosqlitepool/exceptions.py
aiosqlitepool/pool.py
aiosqlitepool/protocols.py
aiosqlitepool-1.0.0.dist-info/licenses/LICENSE
aiosqlitepool-1.0.0.dist-info/METADATA
aiosqlitepool-1.0.0.dist-info/WHEEL
aiosqlitepool-1.0.0.dist-info/top_level.txt
aiosqlitepool-1.0.0.dist-info/RECORD
