Metadata-Version: 2.4
Name: aiosqlitepool
Version: 1.0.0
Summary: A robust, high-performance asynchronous connection pool for SQLite.
Author-email: Iliyan Slavov <iliyan.n.slavov@gmail.com>
License-Expression: MIT
Project-URL: Homepage, https://github.com/slaily/aiosqlitepool
Project-URL: Bug Tracker, https://github.com/slaily/aiosqlitepool/issues
Project-URL: Source Code, https://github.com/slaily/aiosqlitepool
Classifier: Development Status :: 5 - Production/Stable
Classifier: Intended Audience :: Developers
Classifier: Programming Language :: Python :: 3.8
Classifier: Programming Language :: Python :: 3.9
Classifier: Programming Language :: Python :: 3.10
Classifier: Programming Language :: Python :: 3.11
Classifier: Programming Language :: Python :: 3.12
Classifier: Topic :: Database
Classifier: Framework :: AsyncIO
Requires-Python: >=3.8
License-File: LICENSE
Dynamic: license-file
